Workbook

Sheet Финальная анкета
A1: ДЫМОВ 25. 100 ШАГОВ НА ПУТИ К УСПЕХУ — ОФИС / ФИНАЛЬНАЯ ВЕРСИЯ
A2: Ровно 100 определений вопросов. Корпоративный блок сохранён полностью. Добавлены площадка, ИИ и финальные вопросы доверия. Ориентир для сайта: около 25 минут.
A3: Важно: вопрос о городе/площадке используется только для агрегированного анализа; отдельные срезы по малым группам не публиковать. Рекомендуемый порог анонимности — не менее 10 ответов на группу.
A5: № | B5: ID сайта | C5: Блок | D5: Подблок | E5: Вопрос | F5: Тип ответа | G5: Варианты ответа | H5: Обязательный | I5: Условие показа | J5: Исходный Q / статус
A6: 1 | B6: OFF_Q001 | C6: eNPS | E6: Насколько вероятно, что вы порекомендуете «Дымов» знакомому как хорошее место работы? | F6: Шкала 0–10 | G6: 0; 1; 2; 3; 4; 5; 6; 7; 8; 9; 10 | H6: Да | I6: Всем | J6: 1 / Сохранён
A7: 2 | B7: OFF_Q002 | C7: Вовлечённость | E7: Я понимаю, какого результата от меня ожидают. | F7: Шкала 1–5 | G7: 1 — полностью не согласен; 5 — полностью согласен | H7: Да | I7: Всем | J7: 2 / Сохранён
A8: 3 | B8: OFF_Q003 | C8: Вовлечённость | E8: Я понимаю, как моя работа влияет на общий результат компании. | F8: Шкала 1–5 | G8: 1 — полностью не согласен; 5 — полностью согласен | H8: Да | I8: Всем | J8: 3 / Сохранён
A9: 4 | B9: OFF_Q006 | C9: Вовлечённость | E9: Я могу проявлять инициативу и предлагать новые решения. | F9: Шкала 1–5 | G9: 1 — полностью не согласен; 5 — полностью согласен | H9: Да | I9: Всем | J9: 6 / Сохранён
A10: 5 | B10: OFF_Q007 | C10: Вовлечённость | E10: Я горжусь тем, что работаю в «Дымов». | F10: Шкала 1–5 | G10: 1 — полностью не согласен; 5 — полностью согласен | H10: Да | I10: Всем | J10: 7 / Сохранён
A11: 6 | B11: OFF_Q008 | C11: Вовлечённость | E11: Среда в компании мотивирует меня достигать результата выше формально ожидаемого. | F11: Шкала 1–5 | G11: 1 — полностью не согласен; 5 — полностью согласен | H11: Да | I11: Всем | J11: 8 / Сохранён
A12: 7 | B12: OFF_Q009 | C12: Вовлечённость | E12: Я регулярно вижу конкретный результат своей работы. | F12: Шкала 1–5 | G12: 1 — полностью не согласен; 5 — полностью согласен | H12: Да | I12: Всем | J12: 9 / Сохранён
A13: 8 | B13: OFF_Q011 | C13: Вовлечённость | E13: Я понимаю, по каким признакам могу оценить, что хорошо справляюсь со своей работой. | F13: Шкала 1–5 | G13: 1 — полностью не согласен; 5 — полностью согласен | H13: Да | I13: Всем | J13: 11 / Сохранён
A14: 9 | B14: OFF_Q012 | C14: Вовлечённость | E14: Что чаще всего мешает вам чувствовать результат и завершённость своей работы и что помогло бы это изменить? | F14: Длинный текст | H14: Нет | I14: Всем | J14: 12 / Объединён / уточнён
A15: 10 | B15: OFF_Q016 | C15: Эффективность | E15: Я понимаю, куда обратиться, если сталкиваюсь с повторяющейся рабочей проблемой. | F15: Шкала 1–5 | G15: 1 — полностью не согласен; 5 — полностью согласен | H15: Да | I15: Всем | J15: 16 / Сохранён
A16: 11 | B16: OFF_Q017 | C16: Эффективность | E16: Если я озвучиваю проблему или предложение, я понимаю, что с ним происходит дальше. | F16: Шкала 1–5 | G16: 1 — полностью не согласен; 5 — полностью согласен | H16: Да | I16: Всем | J16: 17 / Сохранён
A17: 12 | B17: OFF_Q018 | C17: Эффективность | E17: Мне не приходится регулярно выполнять лишние ручные действия из-за ограничений рабочих систем. | F17: Шкала 1–5 | G17: 1 — полностью не согласен; 5 — полностью согласен | H17: Да | I17: Всем | J17: 18 / Сохранён
A18: 13 | B18: OFF_Q019 | C18: Эффективность | E18: У меня есть все необходимые доступы к системам и информации для выполнения моей работы. | F18: Шкала 1–5 | G18: 1 — полностью не согласен; 5 — полностью согласен | H18: Да | I18: Всем | J18: 19 / Сохранён
A19: 14 | B19: OFF_Q020 | C19: Эффективность | E19: Если возникает техническая проблема, я понимаю, куда обратиться и могу получить решение в приемлемый срок. | F19: Шкала 1–5 | G19: 1 — полностью не согласен; 5 — полностью согласен | H19: Да | I19: Всем | J19: 20 / Сохранён
A20: 15 | B20: OFF_AI_01 | C20: Эффективность | D20: ИИ и рабочие инструменты | E20: Используете ли вы инструменты искусственного интеллекта в своей работе? | F20: Один вариант | G20: Да, регулярно; Да, время от времени; Пробовал(а), но практически не использую; Нет, не использую | H20: Да | I20: Всем | J20: NEW / Новый
A21: 16 | B21: OFF_AI_02 | C21: Эффективность | D21: ИИ и рабочие инструменты | E21: Какими инструментами ИИ вы пользуетесь в работе? Выберите все подходящие варианты. | F21: Несколько вариантов | G21: ChatGPT; Microsoft Copilot; Gemini; Claude; Perplexity; GigaChat; YandexGPT; Другой | H21: Да | I21: Если OFF_AI_01 = «Да, регулярно» или «Да, время от времени» | J21: NEW / Новый
A22: 17 | B22: OFF_AI_03 | C22: Эффективность | D22: ИИ и рабочие инструменты | E22: Какой версией или типом доступа к ИИ-инструментам вы преимущественно пользуетесь? | F22: Один вариант | G22: Бесплатная версия; Личная платная версия; Оплачивает компания / корпоративный доступ; Использую и бесплатные, и платные версии; Не знаю; Другое | H22: Да | I22: Если OFF_AI_01 = «Да, регулярно» или «Да, время от времени» | J22: NEW / Новый
A23: 18 | B23: OFF_AI_05 | C23: Эффективность | D23: ИИ и рабочие инструменты | E23: В каких рабочих задачах ИИ приносит вам наибольшую пользу? | F23: Длинный текст | H23: Нет | I23: Если OFF_AI_01 = «Да, регулярно» или «Да, время от времени» | J23: NEW / Новый
A24: 19 | B24: OFF_AI_06 | C24: Эффективность | D24: ИИ и рабочие инструменты | E24: Могли бы инструменты ИИ быть полезны вам в работе? | F24: Один вариант | G24: Да; Скорее да; Скорее нет; Нет; Не знаю, как их можно применить в моей работе | H24: Да | I24: Если OFF_AI_01 = «Пробовал(а), но практически не использую» или «Нет, не использую» | J24: NEW / Новый
A25: 20 | B25: OFF_AI_07 | C25: Эффективность | D25: ИИ и рабочие инструменты | E25: Как вы могли бы применять ИИ в своей работе? | F25: Длинный текст | H25: Нет | I25: Если OFF_AI_01 = «Пробовал(а), но практически не использую» или «Нет, не использую» | J25: NEW / Новый
A26: 21 | B26: OFF_AI_08 | C26: Эффективность | D26: ИИ и рабочие инструменты | E26: Что сегодня мешает вам эффективнее использовать ИИ в работе? Выберите все подходящие варианты. | F26: Несколько вариантов | G26: У меня нет доступа к оплачиваемой версии; Не знаю, какие инструменты подходят; Не понимаю, для каких задач можно использовать ИИ; Не хватает знаний / навыков; Нужно обучение; Нет корпоративного доступа; Есть ограничения по работе с корпоративными / конфиденциальными данными; Не доверяю качеству ответов; Не понимаю, какие данные можно передавать ИИ; В моей работе ИИ не требуется; Ничего не мешает; Другое | H26: Да | I26: Всем | J26: NEW / Новый
A27: 22 | B27: OFF_AI_09 | C27: Эффективность | D27: ИИ и рабочие инструменты | E27: Что помогло бы вам эффективнее использовать ИИ в работе? Выберите все подходящие варианты. | F27: Несколько вариантов | G27: Доступ к платной версии; Корпоративный доступ; Базовое обучение; Обучение под задачи моей функции; Примеры и готовые сценарии использования; Понятные правила компании по работе с ИИ и данными; Консультация специалиста; Ничего не требуется; Другое | H27: Да | I27: Всем | J27: NEW / Новый
A28: 23 | B28: OFF_Q021 | C28: Эффективность | E28: Какая программа, система или рабочий процесс сегодня отнимает у вас лишнее время и что в нём необходимо изменить или автоматизировать? | F28: Длинный текст | H28: Нет | I28: Всем | J28: 21 / Объединён / уточнён
A29: 24 | B29: OFF_Q023 | C29: Эффективность | E29: Проблемы, которые регулярно повторяются, в конечном итоге устраняются, а не только решаются каждый раз вручную. | F29: Шкала 1–5 | G29: 1 — полностью не согласен; 5 — полностью согласен | H29: Да | I29: Всем | J29: 23 / Сохранён
A30: 25 | B30: OFF_Q024 | C30: Эффективность | E30: Компания достаточно быстро реагирует на проблемы, которые мешают работе сотрудников. | F30: Шкала 1–5 | G30: 1 — полностью не согласен; 5 — полностью согласен | H30: Да | I30: Всем | J30: 24 / Сохранён
A31: 26 | B31: OFF_Q025 | C31: Эффективность | E31: Какой процесс в компании, на ваш взгляд, давно необходимо изменить или упростить? | F31: Длинный текст | H31: Нет | I31: Всем | J31: 25 / Сохранён
A32: 27 | B32: OFF_Q026 | C32: Эффективность | E32: Как часто вам приходится выполнять рабочие задачи за пределами установленного рабочего времени? | F32: Один вариант | G32: Никогда; Редко; Иногда; Часто; Практически постоянно | H32: Да | I32: Всем | J32: 26 / Сохранён
A33: 28 | B33: OFF_Q027 | C33: Эффективность | E33: Рабочие задачи обычно позволяют мне сохранять достаточно времени для личной жизни и отдыха. | F33: Шкала 1–5 | G33: 1 — полностью не согласен; 5 — полностью согласен | H33: Да | I33: Всем | J33: 27 / Сохранён
A34: 29 | B34: OFF_Q029 | C34: Эффективность | E34: После окончания рабочего дня я могу действительно отключиться от рабочих вопросов. | F34: Шкала 1–5 | G34: 1 — полностью не согласен; 5 — полностью согласен | H34: Да | I34: Всем | J34: 29 / Сохранён
A35: 30 | B35: OFF_Q031 | C35: Руководитель | E35: Мой руководитель понятно ставит задачи и приоритеты. | F35: Шкала 1–5 | G35: 1 — полностью не согласен; 5 — полностью согласен | H35: Да | I35: Всем | J35: 31 / Сохранён
A36: 31 | B36: OFF_Q032 | C36: Руководитель | E36: Руководитель относится ко мне уважительно. | F36: Шкала 1–5 | G36: 1 — полностью не согласен; 5 — полностью согласен | H36: Да | I36: Всем | J36: 32 / Сохранён
A37: 32 | B37: OFF_Q033 | C37: Руководитель | E37: Я считаю, что руководитель справедливо оценивает мою работу и вклад. | F37: Шкала 1–5 | G37: 1 — полностью не согласен; 5 — полностью согласен | H37: Да | I37: Всем | J37: 33 / Сохранён
A38: 33 | B38: OFF_Q034 | C38: Руководитель | E38: Я регулярно получаю полезную обратную связь. | F38: Шкала 1–5 | G38: 1 — полностью не согласен; 5 — полностью согласен | H38: Да | I38: Всем | J38: 34 / Сохранён
A39: 34 | B39: OFF_Q035 | C39: Руководитель | E39: Я могу открыто говорить руководителю о проблемах и предлагать идеи. | F39: Шкала 1–5 | G39: 1 — полностью не согласен; 5 — полностью согласен | H39: Да | I39: Всем | J39: 35 / Сохранён
A40: 35 | B40: OFF_Q037 | C40: Руководитель | E40: Я считаю, что основные правила и требования применяются к сотрудникам последовательно и одинаково. | F40: Шкала 1–5 | G40: 1 — полностью не согласен; 5 — полностью согласен | H40: Да | I40: Всем | J40: 37 / Сохранён
A41: 36 | B41: OFF_Q038 | C41: Руководитель | E41: В моём подразделении рабочая нагрузка и ответственность распределяются справедливо. | F41: Шкала 1–5 | G41: 1 — полностью не согласен; 5 — полностью согласен | H41: Да | I41: Всем | J41: 38 / Сохранён
A42: 37 | B42: OFF_Q039 | C42: Руководитель | E42: В каких вопросах или ситуациях вам сегодня больше всего не хватает ощущения справедливости? | F42: Длинный текст | H42: Нет | I42: Всем | J42: 39 / Сохранён
A43: 38 | B43: OFF_Q040 | C43: Самостоятельность | E43: Уровень полномочий позволяет мне реально влиять на результат в своей зоне ответственности. | F43: Шкала 1–5 | G43: 1 — полностью не согласен; 5 — полностью согласен | H43: Да | I43: Всем | J43: 40 / Сохранён
A44: 39 | B44: OFF_Q041 | C44: Самостоятельность | E44: Я могу отстаивать профессиональную позицию, даже если она отличается от мнения руководителя или смежной функции. | F44: Шкала 1–5 | G44: 1 — полностью не согласен; 5 — полностью согласен | H44: Да | I44: Всем | J44: 41 / Сохранён
A45: 40 | B45: OFF_Q043 | C45: Топ-менеджмент | E45: Я доверяю качеству ключевых бизнес-решений, принимаемых руководством компании. | F45: Шкала 1–5 | G45: 1 — полностью не согласен; 5 — полностью согласен | H45: Да | I45: Всем | J45: 43 / Сохранён
A46: 41 | B46: OFF_Q044 | C46: Топ-менеджмент | E46: Я понимаю, как цели моего подразделения связаны с общими целями компании. | F46: Шкала 1–5 | G46: 1 — полностью не согласен; 5 — полностью согласен | H46: Да | I46: Всем | J46: 44 / Сохранён
A47: 42 | B47: OFF_Q045 | C47: Топ-менеджмент | E47: При значимых изменениях мне достаточно понятно объясняют, почему компания принимает то или иное решение. | F47: Шкала 1–5 | G47: 1 — полностью не согласен; 5 — полностью согласен | H47: Да | I47: Всем | J47: 45 / Сохранён
A48: 43 | B48: OFF_Q046 | C48: Топ-менеджмент | E48: Решения, которые непосредственно касаются сотрудников, обычно принимаются понятным и справедливым образом. | F48: Шкала 1–5 | G48: 1 — полностью не согласен; 5 — полностью согласен | H48: Да | I48: Всем | J48: 46 / Сохранён
A49: 44 | B49: OFF_Q047 | C49: Топ-менеджмент | E49: Какой информации о целях, планах или решениях компании вам сегодня не хватает и что стоило бы изменить в коммуникации с сотрудниками? | F49: Длинный текст | H49: Нет | I49: Всем | J49: 47 / Объединён / уточнён
A50: 45 | B50: OFF_Q050 | C50: Признание | E50: Я получаю признание или благодарность, когда действительно делаю значимый результат. | F50: Шкала 1–5 | G50: 1 — полностью не согласен; 5 — полностью согласен | H50: Да | I50: Всем | J50: 50 / Сохранён
A51: 46 | B51: OFF_Q051 | C51: Признание | E51: Какая форма признания лично для вас действительно имеет ценность? Выберите до 3. | F51: Несколько вариантов, до 3 | G51: Личная благодарность руководителя; Публичное признание; Денежное вознаграждение; Дополнительная премия; Возможность участвовать в более значимых проектах; Профессиональное развитие / обучение; Расширение ответственности; Карьерное продвижение; Дополнительный выходной; Подарок / сертификат; Мне достаточно понимать, что мой результат замечен | H51: Да | I51: Всем | J51: 51 / Сохранён
A52: 47 | B52: OFF_Q053 | C52: Намерение продолжать работу в компании | E52: Насколько вероятно, что вы будете продолжать работать в компании через ближайшие 12 месяцев? | F52: Шкала 1–5 | G52: 1 — совершенно не вероятно; 5 — очень вероятно | H52: Да | I52: Всем | J52: 53 / Сохранён
A53: 48 | B53: OFF_Q054 | C53: Намерение продолжать работу в компании | E53: Как часто за последние 6 месяцев вы серьёзно задумывались о смене места работы? | F53: Один вариант | G53: Ни разу; Один-два раза; Иногда; Часто; В настоящее время рассматриваю варианты; Предпочитаю не отвечать | H53: Да | I53: Всем | J53: 54 / Сохранён
A54: 49 | B54: OFF_Q057 | C54: Развитие и карьера | E54: Текущие задачи и проекты позволяют мне усиливать профессиональную экспертизу. | F54: Шкала 1–5 | G54: 1 — полностью не согласен; 5 — полностью согласен | H54: Да | I54: Всем | J54: 57 / Сохранён
A55: 50 | B55: OFF_Q059 | C55: Развитие и карьера | E55: Я вижу для себя понятные возможности профессионального и карьерного развития в «Дымов». | F55: Шкала 1–5 | G55: 1 — полностью не согласен; 5 — полностью согласен | H55: Да | I55: Всем | J55: 59 / Сохранён
A56: 51 | B56: OFF_Q060 | C56: Приоритеты | E56: Какие факторы сегодня наиболее важны лично для вашей результативности? Выберите до 5. | F56: Несколько вариантов, до 5 | G56: Ясность стратегии; Сильный руководитель; Самостоятельность и полномочия; Признание результата; Финансовая мотивация; Профессиональное развитие; Сильная команда; Качественная аналитика; Скорость принятия решений; Взаимодействие между подразделениями; IT-инструменты; Карьерные возможности; Другое | H56: Да | I56: Всем | J56: 60 / Сохранён
A57: 52 | B57: OFF_Q062 | C57: Климат | E57: Коллеги помогают друг другу. | F57: Шкала 1–5 | G57: 1 — полностью не согласен; 5 — полностью согласен | H57: Да | I57: Всем | J57: 62 / Сохранён
A58: 53 | B58: OFF_Q064 | C58: Климат | E58: Между подразделениями достаточно хорошее взаимодействие. | F58: Шкала 1–5 | G58: 1 — полностью не согласен; 5 — полностью согласен | H58: Да | I58: Всем | J58: 64 / Сохранён
A59: 54 | B59: OFF_Q065 | C59: Климат | E59: Я чувствую себя частью общей команды «Дымов». | F59: Шкала 1–5 | G59: 1 — полностью не согласен; 5 — полностью согласен | H59: Да | I59: Всем | J59: 65 / Сохранён
A60: 55 | B60: OFF_Q066 | C60: Климат | E60: Я могу сообщить о рабочей проблеме или риске, не опасаясь, что сам факт такого сообщения приведёт к негативному отношению ко мне. | F60: Шкала 1–5 | G60: 1 — полностью не согласен; 5 — полностью согласен | H60: Да | I60: Всем | J60: 66 / Сохранён
A61: 56 | B61: OFF_Q067 | C61: Климат | E61: Если я допускаю ошибку, я могу открыто сообщить о ней и сосредоточиться на её исправлении, не пытаясь её скрыть. | F61: Шкала 1–5 | G61: 1 — полностью не согласен; 5 — полностью согласен | H61: Да | I61: Всем | J61: 67 / Сохранён
A62: 57 | B62: OFF_Q069 | C62: Климат | E62: Я могу обратиться за помощью к коллегам или руководителю, если самостоятельно не могу решить рабочую задачу. | F62: Шкала 1–5 | G62: 1 — полностью не согласен; 5 — полностью согласен | H62: Да | I62: Всем | J62: 69 / Сохранён
A63: 58 | B63: OFF_Q071 | C63: Климат | E63: Есть ли ситуации, в которых сотруднику сложно открыто сообщить о проблеме, ошибке или попросить помощи? Что этому мешает? | F63: Длинный текст | H63: Нет | I63: Всем | J63: 71 / Сохранён
A64: 59 | B64: OFF_LOC_01 | C64: Условия | D64: Площадка | E64: Укажите город и площадку / адрес, где вы преимущественно работаете. | F64: Короткий текст | H64: Да | I64: Всем | J64: NEW / Новый
A65: 60 | B65: OFF_Q074 | C65: Условия | E65: Есть ли у вас возможность сосредоточиться, когда задача требует тишины? | F65: Шкала 1–5 | G65: 1 — практически нет; 5 — полностью есть | H65: Да | I65: Всем | J65: 74 / Сохранён
A66: 61 | B66: OFF_Q079 | C66: Условия / обучение | E66: Есть ли у вас потребность в дополнительном обучении в рамках вашей должности (тренинги, повышение квалификации, профессиональные курсы и т. д.)? | F66: Один вариант | G66: Да, есть высокая потребность; Скорее да; Скорее нет; Нет, дополнительное обучение не требуется; Затрудняюсь ответить | H66: Нет | I66: Всем | J66: 79 / Сохранён
A67: 62 | B67: OFF_Q080 | C67: Условия | E67: Моё рабочее место организовано удобно для выполнения задач. | F67: Шкала 1–5 | G67: 1 — полностью не согласен; 5 — полностью согласен | H67: Да | I67: Всем | J67: 80 / Сохранён
A68: 63 | B68: OFF_Q081 | C68: Условия | E68: Мне хватает необходимой техники, оборудования и рабочих инструментов. | F68: Шкала 1–5 | G68: 1 — полностью не согласен; 5 — полностью согласен | H68: Да | I68: Всем | J68: 81 / Сохранён
A69: 64 | B69: OFF_Q082 | C69: Условия | E69: Техника и оборудование, которыми я пользуюсь, находятся в подходящем рабочем состоянии. | F69: Шкала 1–5 | G69: 1 — полностью не согласен; 5 — полностью согласен | H69: Нет | I69: Всем | J69: 82 / Сохранён
A70: 65 | B70: OFF_Q083 | C70: Условия | E70: Меня устраивает место для приёма пищи — корпоративная столовая. | F70: Шкала 1–5 + Н/П | G70: 1 — совершенно не устраивает; 5 — полностью устраивает; Не пользуюсь | H70: Нет | I70: Всем | J70: 83 / Сохранён
A71: 66 | B71: OFF_Q084 | C71: Условия | E71: Меня устраивает качество питания, если я им пользуюсь. | F71: Шкала 1–5 + Н/П | G71: 1 — совершенно не устраивает; 5 — полностью устраивает; Не пользуюсь | H71: Нет | I71: Всем | J71: 84 / Сохранён
A72: 67 | B72: OFF_Q085 | C72: Условия | E72: У меня есть подходящее место для отдыха / короткого восстановления в течение рабочего дня. | F72: Шкала 1–5 | G72: 1 — полностью не согласен; 5 — полностью согласен | H72: Нет | I72: Всем | J72: 85 / Сохранён
A73: 68 | B73: OFF_Q086 | C73: Условия | E73: Меня устраивает мой график работы. | F73: Шкала 1–5 | G73: 1 — совершенно не устраивает; 5 — полностью устраивает | H73: Нет | I73: Всем | J73: 86 / Сохранён
A74: 69 | B74: OFF_Q087 | C74: Условия | E74: Меня устраивает организация корпоративного транспорта, если я им пользуюсь. | F74: Шкала 1–5 + Н/П | G74: 1 — совершенно не устраивает; 5 — полностью устраивает; Не пользуюсь | H74: Нет | I74: Всем | J74: 87 / Сохранён
A75: 70 | B75: OFF_Q088 | C75: Условия | E75: Что в офисных условиях хотелось бы улучшить в первую очередь? | F75: Несколько вариантов, до 3 | G75: Оборудовать кофе-зону; Установить автомат/вендинговый холодильник с готовой едой; Улучшить корпоративную столовую / место для приёма пищи; Оборудовать зону отдыха на улице; Улучшить рабочее место: мебель, освещение, температура; Улучшить переговорные и общие зоны; Улучшить санитарно-бытовые условия; Снизить уровень шума / создать тихие зоны для концентрации; Ничего менять не нужно; Другое | H75: Да | I75: Всем | J75: 88 / Уточнён
A76: 71 | B76: OFF_Q089 | C76: Самочувствие и благополучие | E76: Как бы вы в целом оценили своё настроение в течение последних 4 недель? | F76: Шкала 1–5 | G76: 1 — преимущественно очень плохое; 5 — преимущественно очень хорошее | H76: Да | I76: Всем | J76: 89 / Сохранён
... A81: 76 | B81: OFF_Q097 | C81: Самочувствие и благополучие | E81: Что сейчас сильнее всего влияет на ваше общее самочувствие? Выберите до 3 вариантов. | F81: Несколько вариантов, до 3 | G81: Рабочая нагрузка; Содержание работы; Неопределённость / частые изменения; Отношения с руководителем; Отношения с коллегами; Финансовые вопросы; Состояние здоровья; Недостаток отдыха / сна; Семейные или личные обстоятельства; Длительная дорога на работу; Причины, не связанные с работой; Затрудняюсь ответить; Предпочитаю не отвечать; Другое | H81: Да | I81: Всем | J81: 97 / Сохранён
A82: 77 | B82: OFF_Q099 | C82: Самочувствие и благополучие | E82: Что со стороны компании или организации работы могло бы улучшить ситуацию? | F82: Длинный текст | H82: Нет | I82: Всем | J82: 99 / Сохранён
A83: 78 | B83: OFF_Q100 | C83: Гордость за компанию | E83: Мне приятно рассказывать другим людям о том, где я работаю. | F83: Шкала 1–5 | G83: 1 — полностью не согласен; 5 — полностью согласен | H83: Да | I83: Всем | J83: 100 / Сохранён
A84: 79 | B84: OFF_Q102 | C84: Гордость за компанию | E84: Что в «Дымов» вызывает у вас наибольшую гордость? | F84: Длинный текст | H84: Нет | I84: Всем | J84: 102 / Сохранён
A85: 80 | B85: OFF_Q103 | C85: Гордость за компанию | E85: Какие сильные стороны «Дымов» для вас наиболее важны? | F85: Несколько вариантов, до 5 | G85: Стабильность компании; Известный бренд; Продукция компании; Коллектив; Руководитель; Уровень заработной платы; Социальные гарантии; Возможность профессионального развития; Возможность карьерного роста; Условия труда; Отношение к сотрудникам; Атмосфера в компании; Масштаб и возможности компании; Интересные задачи; Возможность проявлять инициативу; Другое | H85: Да | I85: Всем | J85: 103 / Сохранён
A86: 81 | B86: OFF_Q105 | C86: Насколько человеку подходит компания | E86: Мне подходит принятый в компании стиль работы и взаимодействия. | F86: Шкала 1–5 | G86: 1 — полностью не согласен; 5 — полностью согласен | H86: Да | I86: Всем | J86: 105 / Сохранён
A87: 82 | B87: OFF_Q106 | C87: Насколько человеку подходит компания | E87: Мне комфортны темп работы и способы принятия решений в компании. | F87: Шкала 1–5 | G87: 1 — полностью не согласен; 5 — полностью согласен | H87: Да | I87: Всем | J87: 106 / Сохранён
A88: 83 | B88: OFF_Q107 | C88: Насколько человеку подходит компания | E88: Я чувствую, что могу быть успешным сотрудником именно в этой компании. | F88: Шкала 1–5 | G88: 1 — полностью не согласен; 5 — полностью согласен | H88: Да | I88: Всем | J88: 107 / Сохранён
A89: 84 | B89: OFF_Q110 | C89: Насколько человеку подходит компания | E89: Какие слабые стороны сегодня сильнее всего снижают вашу вовлечённость? | F89: Несколько вариантов, до 5 | G89: Сложные процессы; Долгие согласования; Высокая нагрузка; Недостаток сотрудников; Недостаток информации; Взаимодействие между подразделениями; Отношение руководителей; Несправедливая оценка; Недостаток признания; Недостаток развития; Условия работы; Система оплаты / премирования; Другое | H89: Да | I89: Всем | J89: 110 / Сохранён
A90: 85 | B90: OFF_Q114 | C90: Вознаграждение | E90: Я считаю уровень своего вознаграждения соответствующим объёму ответственности и достигнутым результатам. | F90: Шкала 1–5 | G90: 1 — полностью не согласен; 5 — полностью согласен | H90: Да | I90: Всем | J90: 114 / Сохранён
A91: 86 | B91: OFF_Q115 | C91: Вознаграждение | E91: Я считаю уровень своего вознаграждения конкурентным относительно рынка для специалистов сопоставимого уровня. | F91: Шкала 1–5 | G91: 1 — полностью не согласен; 5 — полностью согласен; Затрудняюсь оценить | H91: Нет | I91: Всем | J91: 115 / Сохранён
A92: 87 | B92: OFF_Q116 | C92: Вознаграждение | E92: Мне понятны принципы формирования оклада, премии и других выплат. | F92: Шкала 1–5 | G92: 1 — полностью не согласен; 5 — полностью согласен | H92: Да | I92: Всем | J92: 116 / Сохранён
A93: 88 | B93: OFF_Q117 | C93: Вознаграждение | E93: Я понимаю, каким образом мой результат влияет на переменную часть вознаграждения, если она предусмотрена. | F93: Шкала 1–5 | G93: 1 — полностью не согласен; 5 — полностью согласен; Н/П | H93: Нет | I93: Всем | J93: 117 / Сохранён
A94: 89 | B94: OFF_Q118 | C94: Вознаграждение | E94: Что для вас важнее всего в системе вознаграждения? Выберите до 3. | F94: Флажки до 3 | G94: Уровень фиксированного дохода; Размер премии; Понятность KPI; Зависимость премии от результата; Справедливость между сотрудниками сопоставимого уровня; Конкурентность относительно рынка; Регулярность пересмотра дохода; Дополнительные льготы / бенефиты; Другое | H94: Да | I94: Всем | J94: 118 / Сохранён
A95: 90 | B95: OFF_Q120 | C95: Корпоратив | E95: Участвовали ли вы в корпоративных мероприятиях «Дымов» за последние 2 года? | F95: Один вариант | G95: Да, несколько раз; Да, один раз; Нет | H95: Да | I95: Всем | J95: 120 / Сохранён
A96: 91 | B96: OFF_Q121 | C96: Корпоратив | E96: Что вам больше всего нравилось в предыдущих мероприятиях? | F96: Несколько вариантов | G96: Атмосфера; Возможность общаться; Программа; Музыка; Еда; Локация; Активности; Выступления коллег; Подарки; Возможность познакомиться с другими бизнесами; Другое | H96: Нет | I96: Всем | J96: 121 / Сохранён
A97: 92 | B97: OFF_Q122 | C97: Корпоратив | E97: Что в прежних корпоративных мероприятиях хотелось бы изменить? | F97: Длинный текст | H97: Нет | I97: Всем | J97: 122 / Сохранён
A98: 93 | B98: OFF_Q123 | C98: Корпоратив | E98: Какой формат корпоративного мероприятия вам наиболее интересен? | F98: Несколько вариантов, до 3 | G98: Большой общий корпоратив всей компании; Мероприятие своей площадки / офиса; Семейный праздник с детьми; Фестиваль; Выезд на природу; Спортивный праздник; Командные соревнования; Интеллектуальные игры / квиз; Концерты и творческая программа сотрудников; Гастрономическое мероприятие; Экскурсии / путешествия; Мастер-классы; Благотворительное мероприятие; Небольшие неформальные встречи командами; Другое | H98: Да | I98: Всем | J98: 123 / Сохранён
A99: 94 | B99: OFF_Q124 | C99: Корпоратив | E99: Какие впечатления вы хотели бы получить от корпоратива? | F99: Несколько вариантов, до 3 | G99: Хорошо отдохнуть; Получить яркие эмоции; Почувствовать гордость за компанию; Почувствовать себя частью большой команды; Познакомиться с коллегами из других подразделений; Узнать людей компании с другой стороны; Почувствовать признание своего вклада; Увидеть заботу компании о сотрудниках; Узнать больше об истории и будущем «Дымов»; Провести время с семьёй; Получить новые впечатления; Другое | H99: Да | I99: Всем | J99: 124 / Сохранён
A100: 95 | B100: OFF_Q125 | C100: Корпоратив | E100: Чего вы точно НЕ хотели бы видеть на корпоративе? | F100: Длинный текст | H100: Нет | I100: Всем | J100: 125 / Сохранён
A101: 96 | B101: OFF_Q126 | C101: Корпоратив | E101: Предложите свой формат или идею корпоративного мероприятия. | F101: Длинный текст | H101: Нет | I101: Всем | J101: 126 / Сохранён
A102: 97 | B102: OFF_Q128 | C102: Финал | E102: Какие 3 изменения со стороны компании сильнее всего повысили бы ваше желание работать здесь, проявлять инициативу, показывать высокий результат и рекомендовать «Дымов» как работодателя? | F102: Длинный текст | H102: Да | I102: Всем | J102: 128 / Сохранён
A103: 98 | B103: OFF_TRUST_01 | C103: Финал | D103: Доверие к обратной связи | E103: Я верю, что компания действительно будет работать с результатами этого опроса. | F103: Шкала 1–5 | G103: 1 — полностью не согласен; 5 — полностью согласен | H103: Да | I103: После прохождения основных блоков | J103: NEW / Новый
A104: 99 | B104: OFF_TRUST_02 | C104: Финал | D104: Доверие к обратной связи | E104: Я верю, что изменения по итогам опроса будут заметны сотрудникам. | F104: Шкала 1–5 | G104: 1 — полностью не согласен; 5 — полностью согласен | H104: Да | I104: После прохождения основных блоков | J104: NEW / Новый
A105: 100 | B105: OFF_TRUST_03 | C105: Финал | D105: Доверие к обратной связи | E105: Я верю, что мои ответы могут повлиять на реальные улучшения в компании. | F105: Шкала 1–5 | G105: 1 — полностью не согласен; 5 — полностью согласен | H105: Да | I105: После прохождения основных блоков | J105: NEW / Новый

Sheet Сводка
A1: ИТОГ: «100 ШАГОВ НА ПУТИ К УСПЕХУ»
A2: В финальной структуре ровно 100 определений вопросов. Из-за ветвления ИИ сотрудник увидит 97–98 экранов. Ориентир прохождения: около 25 минут.
A4: Блок | B4: Вопросов в таблице | C4: Открытых вопросов | D4: Обязательных | E4: Комментарий | F4: Статус
A5: eNPS | B5: =COUNTIF('Финальная анкета'!$C:$C,A5) | C5: =COUNTIFS('Финальная анкета'!$C:$C,A5,'Финальная анкета'!$F:$F,"*текст*") | D5: =COUNTIFS('Финальная анкета'!$C:$C,A5,'Финальная анкета'!$H:$H,"Да") | E5: Ключевой outcome-показатель. | F5: Оптимизирован
A6: Вовлечённость | B6: =COUNTIF('Финальная анкета'!$C:$C,A6) | C6: =COUNTIFS('Финальная анкета'!$C:$C,A6,'Финальная анкета'!$F:$F,"*текст*") | D6: =COUNTIFS('Финальная анкета'!$C:$C,A6,'Финальная анкета'!$H:$H,"Да") | E6: Сокращено; оставлены ключевые драйверы и один открытый вопрос. | F6: Оптимизирован
A7: Эффективность | B7: =COUNTIF('Финальная анкета'!$C:$C,A7) | C7: =COUNTIFS('Финальная анкета'!$C:$C,A7,'Финальная анкета'!$F:$F,"*текст*") | D7: =COUNTIFS('Финальная анкета'!$C:$C,A7,'Финальная анкета'!$H:$H,"Да") | E7: Включает технологии, процессы, work-life balance и условный блок ИИ. | F7: Оптимизирован
A8: Руководитель | B8: =COUNTIF('Финальная анкета'!$C:$C,A8) | C8: =COUNTIFS('Финальная анкета'!$C:$C,A8,'Финальная анкета'!$F:$F,"*текст*") | D8: =COUNTIFS('Финальная анкета'!$C:$C,A8,'Финальная анкета'!$H:$H,"Да") | E8: Оставлены постановка задач, уважение, обратная связь и справедливость. | F8: Оптимизирован
A9: Самостоятельность | B9: =COUNTIF('Финальная анкета'!$C:$C,A9) | C9: =COUNTIFS('Финальная анкета'!$C:$C,A9,'Финальная анкета'!$F:$F,"*текст*") | D9: =COUNTIFS('Финальная анкета'!$C:$C,A9,'Финальная анкета'!$H:$H,"Да") | E9: Сохранён полностью. | F9: Сохранён полностью
A10: Топ-менеджмент | B10: =COUNTIF('Финальная анкета'!$C:$C,A10) | C10: =COUNTIFS('Финальная анкета'!$C:$C,A10,'Финальная анкета'!$F:$F,"*текст*") | D10: =COUNTIFS('Финальная анкета'!$C:$C,A10,'Финальная анкета'!$H:$H,"Да") | E10: Сокращено до конкретных вопросов + одного открытого. | F10: Оптимизирован
A11: Признание | B11: =COUNTIF('Финальная анкета'!$C:$C,A11) | C11: =COUNTIFS('Финальная анкета'!$C:$C,A11,'Финальная анкета'!$F:$F,"*текст*") | D11: =COUNTIFS('Финальная анкета'!$C:$C,A11,'Финальная анкета'!$H:$H,"Да") | E11: Оставлен личный опыт признания и предпочитаемые формы. | F11: Оптимизирован
A12: Намерение продолжать работу в компании | B12: =COUNTIF('Финальная анкета'!$C:$C,A12) | C12: =COUNTIFS('Финальная анкета'!$C:$C,A12,'Финальная анкета'!$F:$F,"*текст*") | D12: =COUNTIFS('Финальная анкета'!$C:$C,A12,'Финальная анкета'!$H:$H,"Да") | E12: Оставлены 12 месяцев и реальный риск ухода. | F12: Оптимизирован
A13: Развитие и карьера | B13: =COUNTIF('Финальная анкета'!$C:$C,A13) | C13: =COUNTIFS('Финальная анкета'!$C:$C,A13,'Финальная анкета'!$F:$F,"*текст*") | D13: =COUNTIFS('Финальная анкета'!$C:$C,A13,'Финальная анкета'!$H:$H,"Да") | E13: Оставлены развитие экспертизы и карьерные перспективы. | F13: Оптимизирован
A14: Приоритеты | B14: =COUNTIF('Финальная анкета'!$C:$C,A14) | C14: =COUNTIFS('Финальная анкета'!$C:$C,A14,'Финальная анкета'!$F:$F,"*текст*") | D14: =COUNTIFS('Финальная анкета'!$C:$C,A14,'Финальная анкета'!$H:$H,"Да") | E14: Сохранён TOP-факторов результативности. | F14: Оптимизирован
A15: Климат | B15: =COUNTIF('Финальная анкета'!$C:$C,A15) | C15: =COUNTIFS('Финальная анкета'!$C:$C,A15,'Финальная анкета'!$F:$F,"*текст*") | D15: =COUNTIFS('Финальная анкета'!$C:$C,A15,'Финальная анкета'!$H:$H,"Да") | E15: Сохранено ядро командной и психологической безопасности. | F15: Оптимизирован
A16: Условия | B16: =COUNTIF('Финальная анкета'!$C:$C,A16) | C16: =COUNTIFS('Финальная анкета'!$C:$C,A16,'Финальная анкета'!$F:$F,"*текст*") | D16: =COUNTIFS('Финальная анкета'!$C:$C,A16,'Финальная анкета'!$H:$H,"Да") | E16: Добавлена площадка; отдельный шум/кофе/еда/зона отдыха сведены в приоритеты. | F16: Оптимизирован
... A23: Финал | B23: =COUNTIF('Финальная анкета'!$C:$C,A23) | C23: =COUNTIFS('Финальная анкета'!$C:$C,A23,'Финальная анкета'!$F:$F,"*текст*") | D23: =COUNTIFS('Финальная анкета'!$C:$C,A23,'Финальная анкета'!$H:$H,"Да") | E23: Финальный открытый вопрос + 3 вопроса доверия. | F23: Дополнен
A24: ИТОГО определений вопросов | B24: =SUM(B5:B23) | C24: =SUM(C5:C23) | D24: =SUM(D5:D23)
A26: Маршрут сотрудника: 88 сохранённых вопросов из исходной анкеты + 1 площадка + 3 доверия + 4–6 вопросов ИИ по ветке = 97–98 экранов. В таблице ИИ описан 8 строками, потому что две ветки взаимоисключающие.
A27: Время: быстро ≈15–18 мин; нормальное вдумчивое прохождение ≈20–25 мин; с подробными открытыми комментариями ≈25–30 мин. Для сайта рекомендуется писать «около 25 минут».

Sheet Удалено
A1: ВОПРОСЫ, ИСКЛЮЧЁННЫЕ ИЗ ФИНАЛЬНОЙ ВЕРСИИ
A3: Исходный Q | B3: Блок | C3: Вопрос | D3: Причина удаления | E3: Решение
A4: 4 | B4: Вовлечённость | C4: У меня есть необходимые ресурсы и условия, чтобы хорошо выполнять свою работу. | D4: Общий вопрос; ресурсы и условия измеряются подробнее в блоках «Эффективность» и «Условия». | E4: Удалить из основной офисной анкеты
A5: 5 | B5: Вовлечённость | C5: Я чувствую, что мой вклад в компании имеет значение. | D5: Смысловой дубль влияния на общий результат и признания вклада. | E5: Удалить из основной офисной анкеты
A6: 10 | B6: Вовлечённость | C6: В конце рабочего дня / недели у меня обычно есть ощущение, что важные задачи действительно продвинулись или завершены. | D6: Смысловой дубль ощущения конкретного результата; оставлены Q9 и Q11. | E6: Удалить из основной офисной анкеты
A7: 13 | B7: Вовлечённость | C7: Что, на ваш взгляд, помогло бы изменить эту ситуацию? | D7: Объединён с Q12 в один открытый вопрос. | E7: Удалить из основной офисной анкеты
A8: 14 | B8: Эффективность | C8: Мне хватает рабочего времени для выполнения основного объёма задач. | D8: Заменён более фактическими вопросами о работе вне рабочего времени и балансе. | E8: Удалить из основной офисной анкеты
A9: 15 | B9: Эффективность | C9: Существующие процессы помогают выполнять работу, а не создают лишние препятствия. | D9: Слишком общий; процессы измеряются конкретными вопросами Q16–Q24. | E9: Удалить из основной офисной анкеты
A10: 22 | B10: Эффективность | C10: Что конкретно необходимо изменить или автоматизировать? | D10: Объединён с Q21 в один открытый вопрос про систему/процесс и нужное изменение. | E10: Удалить из основной офисной анкеты
A11: 28 | B11: Эффективность | C11: Срочные рабочие вопросы редко требуют от меня менять личные планы или заниматься работой в свободное время. | D11: Дублирует частоту работы вне рабочего времени и возможность отключаться после работы. | E11: Удалить из основной офисной анкеты
A12: 30 | B12: Эффективность | C12: Что в организации работы сильнее всего мешает вам сохранять нормальный баланс между работой и личным временем? | D12: Открытый дубль блока work-life balance; причины видны через другие вопросы. | E12: Удалить из основной офисной анкеты
A13: 36 | B13: Руководитель | C13: Что руководителям компании стоит изменить, чтобы сотрудникам было проще достигать максимального результата? | D13: Слишком общий открытый вопрос; остаются конкретные оценки руководителя и справедливости. | E13: Удалить из основной офисной анкеты
A14: 42 | B14: Топ-менеджмент | C14: Стратегические решения высшего руководства дают понятный ориентир для моей функции. | D14: Более общий стратегический вопрос; оставлен конкретный Q44 о связи целей. | E14: Удалить из основной офисной анкеты
A15: 48 | B15: Топ-менеджмент | C15: Что высшему руководству стоило бы изменить в коммуникации с сотрудниками? | D15: Объединён с Q47 в один открытый вопрос о нехватке информации и коммуникации. | E15: Удалить из основной офисной анкеты
... A43: 127 | B43: Развитие | C43: Что нового вы хотели бы видеть в условиях работы и жизни сотрудников компании? | D43: Общий wishlist дублирует финальный Q128 с приоритизацией изменений. | E43: Удалить из основной офисной анкеты
A44: AI-04 | B44: Эффективность / ИИ и рабочие инструменты | C44: Как вы используете ИИ в своей работе? | D44: Слишком общий открытый вопрос; более содержательный вопрос о конкретных рабочих задачах и пользе ИИ остаётся. | E44: Удалить, чтобы финальная структура содержала ровно 100 вопросов
